{
  "id": "comic-6.625x10.25",
  "name": "Comic 6.625x10.25",
  "platform": "Comic",
  "trimWidth": 6.625,
  "trimHeight": 10.25,
  "overallWidth": 13.6,
  "overallHeight": 10.5,
  "insideMargin": 0.5,
  "outsideMargin": 0.375,
  "topMargin": 0.375,
  "bottomMargin": 0.5,
  "bleed": true,
  "bleedInches": 0.125,
  "mirrorMargins": true,
  "spineWidth": 0.2,
  "barcodeWidth": 2.0,
  "barcodeHeight": 1.2,
  "paper": "Premium",
  "color": "Color",
  "bodyFont": "Arial",
  "headingFont": "Arial Black",
  "bodyFontSize": 10,
  "lineHeight": 1.2,
  "firstLineIndent": 0,
  "minImageDpi": 300
}